SpringKuangjiaRumenjiaochengCYuyanBianchengWangFix1/README.md
SpringKuangjiaRumenjiaochengCYuyanBianchengWangFix1/__init__.py
SpringKuangjiaRumenjiaochengCYuyanBianchengWangFix1/__main__.py
SpringKuangjiaRumenjiaochengCYuyanBianchengWangFix1/file.epub
SpringKuangjiaRumenjiaochengCYuyanBianchengWangFix1/index.html
SpringKuangjiaRumenjiaochengCYuyanBianchengWangFix1/css/__init__.py
SpringKuangjiaRumenjiaochengCYuyanBianchengWangFix1/css/annotations.css
SpringKuangjiaRumenjiaochengCYuyanBianchengWangFix1/css/main.css
SpringKuangjiaRumenjiaochengCYuyanBianchengWangFix1/css/normalize.css
SpringKuangjiaRumenjiaochengCYuyanBianchengWangFix1/css/popup.css
SpringKuangjiaRumenjiaochengCYuyanBianchengWangFix1/font/__init__.py
SpringKuangjiaRumenjiaochengCYuyanBianchengWangFix1/font/fontello.eot
SpringKuangjiaRumenjiaochengCYuyanBianchengWangFix1/font/fontello.svg
SpringKuangjiaRumenjiaochengCYuyanBianchengWangFix1/font/fontello.ttf
SpringKuangjiaRumenjiaochengCYuyanBianchengWangFix1/font/fontello.woff
SpringKuangjiaRumenjiaochengCYuyanBianchengWangFix1/img/__init__.py
SpringKuangjiaRumenjiaochengCYuyanBianchengWangFix1/img/annotator-glyph-sprite.png
SpringKuangjiaRumenjiaochengCYuyanBianchengWangFix1/img/annotator-icon-sprite.png
SpringKuangjiaRumenjiaochengCYuyanBianchengWangFix1/img/apple-touch-icon.png
SpringKuangjiaRumenjiaochengCYuyanBianchengWangFix1/img/cancelfullscreen.png
SpringKuangjiaRumenjiaochengCYuyanBianchengWangFix1/img/close.png
SpringKuangjiaRumenjiaochengCYuyanBianchengWangFix1/img/fullscreen.png
SpringKuangjiaRumenjiaochengCYuyanBianchengWangFix1/img/loader.gif
SpringKuangjiaRumenjiaochengCYuyanBianchengWangFix1/img/menu-icon.png
SpringKuangjiaRumenjiaochengCYuyanBianchengWangFix1/img/save.png
SpringKuangjiaRumenjiaochengCYuyanBianchengWangFix1/img/saved.png
SpringKuangjiaRumenjiaochengCYuyanBianchengWangFix1/img/settings-s.png
SpringKuangjiaRumenjiaochengCYuyanBianchengWangFix1/img/settings.png
spring_kuangjia_rumenjiaocheng_c_yuyan_biancheng_wang_fix1-2025.3.24.0.dist-info/METADATA
spring_kuangjia_rumenjiaocheng_c_yuyan_biancheng_wang_fix1-2025.3.24.0.dist-info/WHEEL
spring_kuangjia_rumenjiaocheng_c_yuyan_biancheng_wang_fix1-2025.3.24.0.dist-info/entry_points.txt
spring_kuangjia_rumenjiaocheng_c_yuyan_biancheng_wang_fix1-2025.3.24.0.dist-info/top_level.txt
spring_kuangjia_rumenjiaocheng_c_yuyan_biancheng_wang_fix1-2025.3.24.0.dist-info/RECORD
